Metadata-Version: 2.1
Name: nonebot_plugin_logstream
Version: 1.0.3
Summary: NoneBot 网页终端实时log显示/输出插件
Home-page: https://github.com/KiKi-XC/nonebot_plugin_logstream
Author: KiKi-XC
Author-email: kiki.work@hotmail.com
License: MIT License
Platform: all
Classifier: Programming Language :: Python :: 3.10
License-File: LICENSE
Requires-Dist: nonebot2>=2.3.3
Requires-Dist: fastapi>=0.114.0
Requires-Dist: ansi2html>=1.9.2
Requires-Dist: sse-starlette>=2.1.3
Requires-Dist: uvicorn>=0.17.6
Requires-Dist: loguru>=0.7.2
Requires-Dist: starlette>=0.37.2
